[{"id":2041,"data":"2026-06-29","hora_inicio":null,"hora_fim":null,"tipo":"Spleisser","notas":null,"created_at":"2026-06-29T15:25:13.443091+00:00","entry_date":null,"project":"POP GREN04","start_time":"07:00","end_time":"12:00","hours":5,"address":"POP","is_auto":false,"dl_tipo":null,"source":null,"source_id":null,"validated":true}, 
 {"id":1946,"data":"2026-06-04","hora_inicio":null,"hora_fim":null,"tipo":"Feriado","notas":null,"created_at":"2026-06-25T20:28:01.874252+00:00","entry_date":null,"project":null,"start_time":null,"end_time":null,"hours":5.9,"address":null,"is_auto":true,"dl_tipo":null,"source":"manual","source_id":null,"validated":true}, 
 {"id":2062,"data":"2026-08-21","hora_inicio":null,"hora_fim":null,"tipo":"Sexta-feira livre","notas":null,"created_at":"2026-06-29T20:35:31.837863+00:00","entry_date":null,"project":"Remunerado","start_time":"00:00","end_time":"00:00","hours":5.9,"address":null,"is_auto":true,"dl_tipo":"sexta","source":null,"source_id":null,"validated":false}, 
 {"id":2003,"data":"2026-05-01","hora_inicio":null,"hora_fim":null,"tipo":"Sexta-feira livre","notas":null,"created_at":"2026-06-26T04:46:03.441603+00:00","entry_date":null,"project":"Remunerado","start_time":"00:00","end_time":"00:00","hours":5.9,"address":null,"is_auto":true,"dl_tipo":"sexta","source":null,"source_id":null,"validated":true}, 
 {"id":2004,"data":"2026-05-15","hora_inicio":null,"hora_fim":null,"tipo":"Sexta-feira livre","notas":null,"created_at":"2026-06-26T04:46:03.47579+00:00","entry_date":null,"project":"Remunerado","start_time":"00:00","end_time":"00:00","hours":5.9,"address":null,"is_auto":true,"dl_tipo":"sexta","source":null,"source_id":null,"validated":true}, 
 {"id":2005,"data":"2026-05-29","hora_inicio":null,"hora_fim":null,"tipo":"Sexta-feira livre","notas":null,"created_at":"2026-06-26T04:46:03.50875+00:00","entry_date":null,"project":"Remunerado","start_time":"00:00","end_time":"00:00","hours":5.9,"address":null,"is_auto":true,"dl_tipo":"sexta","source":null,"source_id":null,"validated":true}, 
 {"id":2061,"data":"2026-08-14","hora_inicio":null,"hora_fim":null,"tipo":"Sexta-feira livre","notas":null,"created_at":"2026-06-29T20:35:31.8384+00:00","entry_date":null,"project":"Remunerado","start_time":"00:00","end_time":"00:00","hours":5.9,"address":null,"is_auto":true,"dl_tipo":"sexta","source":null,"source_id":null,"validated":false}, 
 {"id":2057,"data":"2026-07-31","hora_inicio":null,"hora_fim":null,"tipo":"Sexta-feira livre","notas":null,"created_at":"2026-06-29T20:35:23.966518+00:00","entry_date":null,"project":"Remunerado","start_time":"00:00","end_time":"00:00","hours":5.9,"address":null,"is_auto":true,"dl_tipo":"sexta","source":null,"source_id":null,"validated":true}, 
 {"id":2042,"data":"2026-06-29","hora_inicio":null,"hora_fim":null,"tipo":"Spleisser","notas":null,"created_at":"2026-06-29T15:26:00.998477+00:00","entry_date":null,"project":"POP GREN04","start_time":"12:45","end_time":"15:45","hours":3,"address":"POP","is_auto":false,"dl_tipo":null,"source":null,"source_id":null,"validated":true}, 
 {"id":140,"data":"2026-06-15","hora_inicio":null,"hora_fim":null,"tipo":"Instalação","notas":null,"created_at":"2026-06-21T08:50:51.139575+00:00","entry_date":null,"project":"BUDI-2S","start_time":"07:00","end_time":"12:00","hours":5,"address":null,"is_auto":false,"dl_tipo":null,"source":null,"source_id":null,"validated":true}, 
 {"id":141,"data":"2026-06-15","hora_inicio":null,"hora_fim":null,"tipo":"Instalação","notas":null,"created_at":"2026-06-21T08:51:03.51212+00:00","entry_date":null,"project":"BUDI-2S","start_time":"12:45","end_time":"16:30","hours":3.8,"address":null,"is_auto":false,"dl_tipo":null,"source":null,"source_id":null,"validated":true}, 
 {"id":142,"data":"2026-06-16","hora_inicio":null,"hora_fim":null,"tipo":"Instalação","notas":null,"created_at":"2026-06-21T08:51:25.073458+00:00","entry_date":null,"project":"BUDI-2S","start_time":"07:00","end_time":"12:30","hours":5.5,"address":null,"is_auto":false,"dl_tipo":null,"source":null,"source_id":null,"validated":true}, 
 {"id":143,"data":"2026-06-16","hora_inicio":null,"hora_fim":null,"tipo":"Spleisser","notas":null,"created_at":"2026-06-21T08:51:39.298561+00:00","entry_date":null,"project":"BUDI-2S","start_time":"13:00","end_time":"16:45","hours":3.8,"address":null,"is_auto":false,"dl_tipo":null,"source":null,"source_id":null,"validated":true}, 
 {"id":146,"data":"2026-06-18","hora_inicio":null,"hora_fim":null,"tipo":"Spleisser","notas":null,"created_at":"2026-06-21T08:52:43.873999+00:00","entry_date":null,"project":"POP GREN04","start_time":"07:00","end_time":"12:15","hours":5.3,"address":null,"is_auto":false,"dl_tipo":null,"source":null,"source_id":null,"validated":true}, 
 {"id":147,"data":"2026-06-18","hora_inicio":null,"hora_fim":null,"tipo":"Spleisser","notas":null,"created_at":"2026-06-21T08:52:59.176129+00:00","entry_date":null,"project":"POP GREN04","start_time":"13:00","end_time":"16:00","hours":3,"address":null,"is_auto":false,"dl_tipo":null,"source":null,"source_id":null,"validated":true}, 
 {"id":167,"data":"2026-06-23","hora_inicio":null,"hora_fim":null,"tipo":"Instalação","notas":null,"created_at":"2026-06-21T13:38:35.004128+00:00","entry_date":null,"project":"BUDI-2S","start_time":"07:00","end_time":"12:00","hours":5,"address":"Däderizstrasse 45","is_auto":false,"dl_tipo":null,"source":"agenda_pro","source_id":15,"validated":true}, 
 {"id":168,"data":"2026-06-23","hora_inicio":null,"hora_fim":null,"tipo":"Instalação","notas":null,"created_at":"2026-06-21T13:38:35.715726+00:00","entry_date":null,"project":"BUDI-2S","start_time":"12:45","end_time":"16:20","hours":3.6,"address":"Däderizstrasse 41","is_auto":false,"dl_tipo":null,"source":"agenda_pro","source_id":16,"validated":true}, 
 {"id":166,"data":"2026-06-24","hora_inicio":null,"hora_fim":null,"tipo":"Instalação","notas":null,"created_at":"2026-06-21T13:38:33.838753+00:00","entry_date":null,"project":"BUDI-2S","start_time":"12:45","end_time":"16:15","hours":3.5,"address":"Blumenrainstrasse 26","is_auto":false,"dl_tipo":null,"source":"agenda_pro","source_id":18,"validated":true}, 
 {"id":172,"data":"2026-06-24","hora_inicio":null,"hora_fim":null,"tipo":"Instalação","notas":null,"created_at":"2026-06-21T13:45:41.532146+00:00","entry_date":null,"project":"BUDI-1S","start_time":"07:00","end_time":"12:00","hours":5,"address":"Blumenrainstrasse 28","is_auto":false,"dl_tipo":null,"source":null,"source_id":null,"validated":true}, 
 {"id":2006,"data":"2026-05-08","hora_inicio":null,"hora_fim":null,"tipo":"Sexta-feira livre","notas":null,"created_at":"2026-06-26T04:46:03.640048+00:00","entry_date":null,"project":"Remunerado","start_time":"00:00","end_time":"00:00","hours":5.9,"address":null,"is_auto":true,"dl_tipo":"sexta","source":null,"source_id":null,"validated":true}, 
 {"id":1922,"data":"2026-06-25","hora_inicio":null,"hora_fim":null,"tipo":"Spleisser","notas":null,"created_at":"2026-06-25T09:59:42.435659+00:00","entry_date":null,"project":"POP GREN04","start_time":"09:00","end_time":"12:00","hours":3,"address":"POP GREN04","is_auto":false,"dl_tipo":null,"source":null,"source_id":null,"validated":true}, 
 {"id":1981,"data":"2026-05-31","hora_inicio":null,"hora_fim":null,"tipo":"Total Maio","notas":null,"created_at":"2026-06-25T20:44:08.660903+00:00","entry_date":null,"project":null,"start_time":null,"end_time":null,"hours":107.83,"address":null,"is_auto":true,"dl_tipo":null,"source":"manual","source_id":null,"validated":true}, 
 {"id":2007,"data":"2026-05-22","hora_inicio":null,"hora_fim":null,"tipo":"Sexta-feira livre","notas":null,"created_at":"2026-06-26T04:46:03.640045+00:00","entry_date":null,"project":"Remunerado","start_time":"00:00","end_time":"00:00","hours":5.9,"address":null,"is_auto":true,"dl_tipo":"sexta","source":null,"source_id":null,"validated":true}, 
 {"id":2043,"data":"2026-06-02","hora_inicio":null,"hora_fim":null,"tipo":"Spleisser","notas":null,"created_at":"2026-06-29T18:11:33.143559+00:00","entry_date":null,"project":"POP GREN04","start_time":"07:00","end_time":"12:00","hours":5,"address":null,"is_auto":false,"dl_tipo":null,"source":null,"source_id":null,"validated":true}, 
 {"id":2060,"data":"2026-08-07","hora_inicio":null,"hora_fim":null,"tipo":"Sexta-feira livre","notas":null,"created_at":"2026-06-29T20:35:31.836167+00:00","entry_date":null,"project":"Remunerado","start_time":"00:00","end_time":"00:00","hours":5.9,"address":null,"is_auto":true,"dl_tipo":"sexta","source":null,"source_id":null,"validated":false}, 
 {"id":2059,"data":"2026-07-03","hora_inicio":null,"hora_fim":null,"tipo":"Sexta-feira livre","notas":null,"created_at":"2026-06-29T20:35:23.965931+00:00","entry_date":null,"project":"Remunerado","start_time":"00:00","end_time":"00:00","hours":5.9,"address":null,"is_auto":true,"dl_tipo":"sexta","source":null,"source_id":null,"validated":true}, 
 {"id":2063,"data":"2026-08-28","hora_inicio":null,"hora_fim":null,"tipo":"Sexta-feira livre","notas":null,"created_at":"2026-06-29T20:35:31.839876+00:00","entry_date":null,"project":"Remunerado","start_time":"00:00","end_time":"00:00","hours":5.9,"address":null,"is_auto":true,"dl_tipo":"sexta","source":null,"source_id":null,"validated":false}, 
 {"id":2044,"data":"2026-06-02","hora_inicio":null,"hora_fim":null,"tipo":"Spleisser","notas":null,"created_at":"2026-06-29T18:12:08.61239+00:00","entry_date":null,"project":"POP GREN04","start_time":"12:45","end_time":"16:35","hours":3.8,"address":null,"is_auto":false,"dl_tipo":null,"source":null,"source_id":null,"validated":true}, 
 {"id":2008,"data":"2026-01-31","hora_inicio":null,"hora_fim":null,"tipo":"Saldo Jan-Mar (Abaclick)","notas":null,"created_at":"2026-06-26T05:07:48.296064+00:00","entry_date":null,"project":"Saldo Abaclick (estimado)","start_time":null,"end_time":null,"hours":29,"address":null,"is_auto":false,"dl_tipo":null,"source":"manual","source_id":null,"validated":false}, 
 {"id":2045,"data":"2026-06-03","hora_inicio":null,"hora_fim":null,"tipo":"Instalação","notas":null,"created_at":"2026-06-29T18:12:43.89325+00:00","entry_date":null,"project":"BEP 2S","start_time":"07:00","end_time":"12:00","hours":5,"address":null,"is_auto":false,"dl_tipo":null,"source":null,"source_id":null,"validated":true}, 
 {"id":2046,"data":"2026-06-03","hora_inicio":null,"hora_fim":null,"tipo":"Spleisser","notas":null,"created_at":"2026-06-29T18:13:06.303467+00:00","entry_date":null,"project":"POP GREN04","start_time":"12:45","end_time":"16:00","hours":3.3,"address":null,"is_auto":false,"dl_tipo":null,"source":null,"source_id":null,"validated":true}, 
 {"id":1983,"data":"2026-06-12","hora_inicio":null,"hora_fim":null,"tipo":"Sexta-feira livre","notas":null,"created_at":"2026-06-25T20:45:44.970274+00:00","entry_date":null,"project":"Remunerado","start_time":"00:00","end_time":"00:00","hours":5.9,"address":null,"is_auto":true,"dl_tipo":"sexta","source":null,"source_id":null,"validated":true}, 
 {"id":2015,"data":"2026-06-17","hora_inicio":null,"hora_fim":null,"tipo":"Trabalho","notas":null,"created_at":"2026-06-29T13:51:26.765594+00:00","entry_date":null,"project":"BUDI-2S","start_time":"13:15","end_time":"16:30","hours":3.3,"address":"Blumenrainstrasse 29","is_auto":false,"dl_tipo":null,"source":"agenda_pro","source_id":8,"validated":true}, 
 {"id":2017,"data":"2026-06-17","hora_inicio":null,"hora_fim":null,"tipo":"Trabalho","notas":null,"created_at":"2026-06-29T13:51:27.358394+00:00","entry_date":null,"project":"BUDI-2S","start_time":"07:00","end_time":"12:00","hours":5,"address":"Blumenrainstrasse 27","is_auto":false,"dl_tipo":null,"source":"agenda_pro","source_id":7,"validated":true}, 
 {"id":2022,"data":"2026-06-22","hora_inicio":null,"hora_fim":null,"tipo":"Trabalho","notas":null,"created_at":"2026-06-29T13:51:28.795862+00:00","entry_date":null,"project":"BUDI-2S","start_time":"12:45","end_time":"16:15","hours":3.5,"address":null,"is_auto":false,"dl_tipo":null,"source":"agenda_pro","source_id":22,"validated":true}, 
 {"id":2033,"data":"2026-06-22","hora_inicio":null,"hora_fim":null,"tipo":"Trabalho","notas":null,"created_at":"2026-06-29T13:51:34.190866+00:00","entry_date":null,"project":"BUDI-2S","start_time":"07:00","end_time":"12:00","hours":5,"address":"Gartenstrasse 2","is_auto":false,"dl_tipo":null,"source":"agenda_pro","source_id":21,"validated":true}, 
 {"id":2064,"data":"2026-07-24","hora_inicio":null,"hora_fim":null,"tipo":"Sexta-feira livre","notas":null,"created_at":"2026-06-29T22:37:11.477586+00:00","entry_date":null,"project":"Remunerado","start_time":"00:00","end_time":"00:00","hours":5.9,"address":null,"is_auto":true,"dl_tipo":"sexta","source":null,"source_id":null,"validated":true}, 
 {"id":1984,"data":"2026-06-05","hora_inicio":null,"hora_fim":null,"tipo":"Sexta-feira livre","notas":null,"created_at":"2026-06-25T20:45:44.970767+00:00","entry_date":null,"project":"Remunerado","start_time":"00:00","end_time":"00:00","hours":5.9,"address":null,"is_auto":true,"dl_tipo":"sexta","source":null,"source_id":null,"validated":true}, 
 {"id":2047,"data":"2026-06-08","hora_inicio":null,"hora_fim":null,"tipo":"Instalação","notas":null,"created_at":"2026-06-29T18:14:44.655157+00:00","entry_date":null,"project":"BEP 2S","start_time":"07:00","end_time":"12:00","hours":5,"address":null,"is_auto":false,"dl_tipo":null,"source":null,"source_id":null,"validated":true}, 
 {"id":2030,"data":"2026-06-25","hora_inicio":null,"hora_fim":null,"tipo":"Trabalho","notas":null,"created_at":"2026-06-29T13:51:33.554381+00:00","entry_date":null,"project":"BUDI-1S","start_time":"07:00","end_time":"09:00","hours":2,"address":"Veilchenstrasse 4","is_auto":false,"dl_tipo":null,"source":"agenda_pro","source_id":23,"validated":true}, 
 {"id":2036,"data":"2026-06-01","hora_inicio":null,"hora_fim":null,"tipo":"Trabalho","notas":null,"created_at":"2026-06-29T13:51:34.84876+00:00","entry_date":null,"project":"BUDI-2S","start_time":"07:00","end_time":"12:00","hours":5,"address":null,"is_auto":false,"dl_tipo":null,"source":"agenda_pro","source_id":24,"validated":true}, 
 {"id":2065,"data":"2026-06-30","hora_inicio":null,"hora_fim":null,"tipo":"Spleisser","notas":null,"created_at":"2026-06-30T07:45:53.78479+00:00","entry_date":null,"project":"POP GREN04","start_time":"07:00","end_time":"12:00","hours":5,"address":null,"is_auto":false,"dl_tipo":null,"source":null,"source_id":null,"validated":true}, 
 {"id":2066,"data":"2026-06-30","hora_inicio":null,"hora_fim":null,"tipo":"Spleisser","notas":null,"created_at":"2026-06-30T09:33:55.669191+00:00","entry_date":null,"project":"POP GREN04","start_time":"12:45","end_time":"15:30","hours":2.8,"address":null,"is_auto":false,"dl_tipo":null,"source":null,"source_id":null,"validated":true}, 
 {"id":2067,"data":"2026-07-01","hora_inicio":null,"hora_fim":null,"tipo":"Instalação","notas":null,"created_at":"2026-07-01T14:33:41.214728+00:00","entry_date":null,"project":"BEP 1S","start_time":"06:50","end_time":"12:20","hours":5.5,"address":null,"is_auto":false,"dl_tipo":null,"source":null,"source_id":null,"validated":true}, 
 {"id":2068,"data":"2026-07-01","hora_inicio":null,"hora_fim":null,"tipo":"Instalação","notas":null,"created_at":"2026-07-01T14:34:01.902701+00:00","entry_date":null,"project":"BEP 1S","start_time":"13:15","end_time":"15:30","hours":2.3,"address":null,"is_auto":false,"dl_tipo":null,"source":null,"source_id":null,"validated":true}, 
 {"id":2049,"data":"2026-06-09","hora_inicio":null,"hora_fim":null,"tipo":"Instalação","notas":null,"created_at":"2026-06-29T18:16:28.929362+00:00","entry_date":null,"project":"BEP 2S","start_time":"07:00","end_time":"12:00","hours":5,"address":null,"is_auto":false,"dl_tipo":null,"source":null,"source_id":null,"validated":true}, 
 {"id":2050,"data":"2026-06-09","hora_inicio":null,"hora_fim":null,"tipo":"Reparação","notas":null,"created_at":"2026-06-29T18:16:53.152774+00:00","entry_date":null,"project":"Nachschiessen","start_time":"12:45","end_time":"16:45","hours":4,"address":null,"is_auto":false,"dl_tipo":null,"source":null,"source_id":null,"validated":true}, 
 {"id":2069,"data":"2026-07-02","hora_inicio":null,"hora_fim":null,"tipo":"Spleisser","notas":null,"created_at":"2026-07-02T12:37:04.993254+00:00","entry_date":null,"project":"POP GREN04","start_time":"06:50","end_time":"12:10","hours":5.3,"address":null,"is_auto":false,"dl_tipo":null,"source":null,"source_id":null,"validated":true}, 
 {"id":2070,"data":"2026-07-02","hora_inicio":null,"hora_fim":null,"tipo":"Inspeção","notas":null,"created_at":"2026-07-02T12:37:32.939284+00:00","entry_date":null,"project":"Magazin","start_time":"13:10","end_time":"15:10","hours":2,"address":null,"is_auto":false,"dl_tipo":null,"source":null,"source_id":null,"validated":true}, 
 {"id":2051,"data":"2026-06-10","hora_inicio":null,"hora_fim":null,"tipo":"Instalação","notas":null,"created_at":"2026-06-29T18:19:21.773418+00:00","entry_date":null,"project":"BEP 2S","start_time":"07:00","end_time":"12:00","hours":5,"address":null,"is_auto":false,"dl_tipo":null,"source":null,"source_id":null,"validated":true}, 
 {"id":2071,"data":"2026-07-17","hora_inicio":null,"hora_fim":null,"tipo":"Sexta-feira livre","notas":null,"created_at":"2026-07-02T14:18:42.746707+00:00","entry_date":null,"project":"Remunerado","start_time":"00:00","end_time":"00:00","hours":5.9,"address":null,"is_auto":true,"dl_tipo":"sexta","source":null,"source_id":null,"validated":false}, 
 {"id":2052,"data":"2026-06-10","hora_inicio":null,"hora_fim":null,"tipo":"Instalação","notas":null,"created_at":"2026-06-29T18:19:51.687429+00:00","entry_date":null,"project":"BEP 2S","start_time":"12:45","end_time":"16:15","hours":3.5,"address":null,"is_auto":false,"dl_tipo":null,"source":null,"source_id":null,"validated":true}, 
 {"id":1991,"data":"2026-06-26","hora_inicio":null,"hora_fim":null,"tipo":"Sexta-feira livre","notas":null,"created_at":"2026-06-25T21:20:22.826339+00:00","entry_date":null,"project":"Remunerado","start_time":"00:00","end_time":"00:00","hours":5.9,"address":null,"is_auto":true,"dl_tipo":"sexta","source":null,"source_id":null,"validated":true}, 
 {"id":2053,"data":"2026-06-11","hora_inicio":null,"hora_fim":null,"tipo":"Instalação","notas":null,"created_at":"2026-06-29T18:20:57.437593+00:00","entry_date":null,"project":"BEP 1S","start_time":"07:00","end_time":"12:00","hours":5,"address":null,"is_auto":false,"dl_tipo":null,"source":null,"source_id":null,"validated":true}, 
 {"id":2072,"data":"2026-07-10","hora_inicio":null,"hora_fim":null,"tipo":"Sexta-feira livre","notas":null,"created_at":"2026-07-02T14:18:42.776577+00:00","entry_date":null,"project":"Remunerado","start_time":"00:00","end_time":"00:00","hours":5.9,"address":null,"is_auto":true,"dl_tipo":"sexta","source":null,"source_id":null,"validated":false}, 
 {"id":2054,"data":"2026-06-11","hora_inicio":null,"hora_fim":null,"tipo":"Spleisser","notas":null,"created_at":"2026-06-29T18:21:20.800637+00:00","entry_date":null,"project":"BEP 1S","start_time":"12:45","end_time":"17:00","hours":4.3,"address":null,"is_auto":false,"dl_tipo":null,"source":null,"source_id":null,"validated":true}, 
 {"id":1998,"data":"2026-04-10","hora_inicio":null,"hora_fim":null,"tipo":"Sexta-feira livre","notas":null,"created_at":"2026-06-25T21:33:39.778785+00:00","entry_date":null,"project":"Remunerado","start_time":"00:00","end_time":"00:00","hours":5.9,"address":null,"is_auto":true,"dl_tipo":"sexta","source":null,"source_id":null,"validated":true}, 
 {"id":1999,"data":"2026-04-24","hora_inicio":null,"hora_fim":null,"tipo":"Sexta-feira livre","notas":null,"created_at":"2026-06-25T21:33:39.778423+00:00","entry_date":null,"project":"Remunerado","start_time":"00:00","end_time":"00:00","hours":5.9,"address":null,"is_auto":true,"dl_tipo":"sexta","source":null,"source_id":null,"validated":true}, 
 {"id":2000,"data":"2026-04-17","hora_inicio":null,"hora_fim":null,"tipo":"Sexta-feira livre","notas":null,"created_at":"2026-06-25T21:33:39.77843+00:00","entry_date":null,"project":"Remunerado","start_time":"00:00","end_time":"00:00","hours":5.9,"address":null,"is_auto":true,"dl_tipo":"sexta","source":null,"source_id":null,"validated":true}, 
 {"id":2001,"data":"2026-04-03","hora_inicio":null,"hora_fim":null,"tipo":"Sexta-feira livre","notas":null,"created_at":"2026-06-25T21:33:39.779242+00:00","entry_date":null,"project":"Remunerado","start_time":"00:00","end_time":"00:00","hours":5.9,"address":null,"is_auto":true,"dl_tipo":"sexta","source":null,"source_id":null,"validated":true}, 
 {"id":2002,"data":"2026-06-19","hora_inicio":null,"hora_fim":null,"tipo":"Sexta-feira livre","notas":null,"created_at":"2026-06-25T22:34:17.604055+00:00","entry_date":null,"project":"Remunerado","start_time":"00:00","end_time":"00:00","hours":5.9,"address":null,"is_auto":true,"dl_tipo":"sexta","source":null,"source_id":null,"validated":true}, 
 {"id":1898,"data":"2026-07-27","hora_inicio":null,"hora_fim":null,"tipo":"Férias","notas":null,"created_at":"2026-06-25T09:11:41.076264+00:00","entry_date":null,"project":"—","start_time":"00:00","end_time":"00:00","hours":5.9,"address":null,"is_auto":true,"dl_tipo":"ferias","source":null,"source_id":null,"validated":true}, 
 {"id":1915,"data":"2026-07-13","hora_inicio":null,"hora_fim":null,"tipo":"Férias","notas":null,"created_at":"2026-06-25T09:11:41.179538+00:00","entry_date":null,"project":"—","start_time":"00:00","end_time":"00:00","hours":5.9,"address":null,"is_auto":true,"dl_tipo":"ferias","source":null,"source_id":null,"validated":true}, 
 {"id":1910,"data":"2026-08-07","hora_inicio":null,"hora_fim":null,"tipo":"Férias","notas":null,"created_at":"2026-06-25T09:11:41.166164+00:00","entry_date":null,"project":"—","start_time":"00:00","end_time":"00:00","hours":5.9,"address":null,"is_auto":true,"dl_tipo":"ferias","source":null,"source_id":null,"validated":false}, 
 {"id":1912,"data":"2026-07-06","hora_inicio":null,"hora_fim":null,"tipo":"Férias","notas":null,"created_at":"2026-06-25T09:11:41.175683+00:00","entry_date":null,"project":"—","start_time":"00:00","end_time":"00:00","hours":5.9,"address":null,"is_auto":true,"dl_tipo":"ferias","source":null,"source_id":null,"validated":true}, 
 {"id":1924,"data":"2026-06-01","hora_inicio":null,"hora_fim":null,"tipo":"Spleisser","notas":null,"created_at":"2026-06-25T19:14:39.234173+00:00","entry_date":null,"project":"BUDI-S","start_time":"12:45","end_time":"16:35","hours":3.8,"address":null,"is_auto":false,"dl_tipo":null,"source":null,"source_id":null,"validated":true}, 
 {"id":1902,"data":"2026-07-16","hora_inicio":null,"hora_fim":null,"tipo":"Férias","notas":null,"created_at":"2026-06-25T09:11:41.076165+00:00","entry_date":null,"project":"—","start_time":"00:00","end_time":"00:00","hours":5.9,"address":null,"is_auto":true,"dl_tipo":"ferias","source":null,"source_id":null,"validated":true}, 
 {"id":1909,"data":"2026-07-28","hora_inicio":null,"hora_fim":null,"tipo":"Férias","notas":null,"created_at":"2026-06-25T09:11:41.166191+00:00","entry_date":null,"project":"—","start_time":"00:00","end_time":"00:00","hours":5.9,"address":null,"is_auto":true,"dl_tipo":"ferias","source":null,"source_id":null,"validated":true}, 
 {"id":1899,"data":"2026-08-03","hora_inicio":null,"hora_fim":null,"tipo":"Férias","notas":null,"created_at":"2026-06-25T09:11:41.10575+00:00","entry_date":null,"project":"—","start_time":"00:00","end_time":"00:00","hours":5.9,"address":null,"is_auto":true,"dl_tipo":"ferias","source":null,"source_id":null,"validated":false}, 
 {"id":1920,"data":"2026-08-04","hora_inicio":null,"hora_fim":null,"tipo":"Férias","notas":null,"created_at":"2026-06-25T09:11:41.186685+00:00","entry_date":null,"project":"—","start_time":"00:00","end_time":"00:00","hours":5.9,"address":null,"is_auto":true,"dl_tipo":"ferias","source":null,"source_id":null,"validated":false}, 
 {"id":1919,"data":"2026-07-09","hora_inicio":null,"hora_fim":null,"tipo":"Férias","notas":null,"created_at":"2026-06-25T09:11:41.175473+00:00","entry_date":null,"project":"—","start_time":"00:00","end_time":"00:00","hours":5.9,"address":null,"is_auto":true,"dl_tipo":"ferias","source":null,"source_id":null,"validated":true}, 
 {"id":1900,"data":"2026-07-10","hora_inicio":null,"hora_fim":null,"tipo":"Férias","notas":null,"created_at":"2026-06-25T09:11:41.074831+00:00","entry_date":null,"project":"—","start_time":"00:00","end_time":"00:00","hours":5.9,"address":null,"is_auto":true,"dl_tipo":"ferias","source":null,"source_id":null,"validated":true}, 
 {"id":1896,"data":"2026-07-30","hora_inicio":null,"hora_fim":null,"tipo":"Férias","notas":null,"created_at":"2026-06-25T09:11:41.075556+00:00","entry_date":null,"project":"—","start_time":"00:00","end_time":"00:00","hours":5.9,"address":null,"is_auto":true,"dl_tipo":"ferias","source":null,"source_id":null,"validated":true}, 
 {"id":1916,"data":"2026-07-20","hora_inicio":null,"hora_fim":null,"tipo":"Férias","notas":null,"created_at":"2026-06-25T09:11:41.180874+00:00","entry_date":null,"project":"—","start_time":"00:00","end_time":"00:00","hours":5.9,"address":null,"is_auto":true,"dl_tipo":"ferias","source":null,"source_id":null,"validated":true}, 
 {"id":1907,"data":"2026-07-22","hora_inicio":null,"hora_fim":null,"tipo":"Férias","notas":null,"created_at":"2026-06-25T09:11:41.168088+00:00","entry_date":null,"project":"—","start_time":"00:00","end_time":"00:00","hours":5.9,"address":null,"is_auto":true,"dl_tipo":"ferias","source":null,"source_id":null,"validated":true}, 
 {"id":1897,"data":"2026-07-29","hora_inicio":null,"hora_fim":null,"tipo":"Férias","notas":null,"created_at":"2026-06-25T09:11:41.100836+00:00","entry_date":null,"project":"—","start_time":"00:00","end_time":"00:00","hours":5.9,"address":null,"is_auto":true,"dl_tipo":"ferias","source":null,"source_id":null,"validated":true}, 
 {"id":1913,"data":"2026-07-07","hora_inicio":null,"hora_fim":null,"tipo":"Férias","notas":null,"created_at":"2026-06-25T09:11:41.175249+00:00","entry_date":null,"project":"—","start_time":"00:00","end_time":"00:00","hours":5.9,"address":null,"is_auto":true,"dl_tipo":"ferias","source":null,"source_id":null,"validated":true}, 
 {"id":1911,"data":"2026-07-31","hora_inicio":null,"hora_fim":null,"tipo":"Férias","notas":null,"created_at":"2026-06-25T09:11:41.166091+00:00","entry_date":null,"project":"—","start_time":"00:00","end_time":"00:00","hours":5.9,"address":null,"is_auto":true,"dl_tipo":"ferias","source":null,"source_id":null,"validated":true}, 
 {"id":1901,"data":"2026-08-06","hora_inicio":null,"hora_fim":null,"tipo":"Férias","notas":null,"created_at":"2026-06-25T09:11:41.08346+00:00","entry_date":null,"project":"—","start_time":"00:00","end_time":"00:00","hours":5.9,"address":null,"is_auto":true,"dl_tipo":"ferias","source":null,"source_id":null,"validated":false}, 
 {"id":1903,"data":"2026-07-14","hora_inicio":null,"hora_fim":null,"tipo":"Férias","notas":null,"created_at":"2026-06-25T09:11:41.074919+00:00","entry_date":null,"project":"—","start_time":"00:00","end_time":"00:00","hours":5.9,"address":null,"is_auto":true,"dl_tipo":"ferias","source":null,"source_id":null,"validated":true}, 
 {"id":1906,"data":"2026-07-15","hora_inicio":null,"hora_fim":null,"tipo":"Férias","notas":null,"created_at":"2026-06-25T09:11:41.167273+00:00","entry_date":null,"project":"—","start_time":"00:00","end_time":"00:00","hours":5.9,"address":null,"is_auto":true,"dl_tipo":"ferias","source":null,"source_id":null,"validated":true}, 
 {"id":1917,"data":"2026-07-21","hora_inicio":null,"hora_fim":null,"tipo":"Férias","notas":null,"created_at":"2026-06-25T09:11:41.178734+00:00","entry_date":null,"project":"—","start_time":"00:00","end_time":"00:00","hours":5.9,"address":null,"is_auto":true,"dl_tipo":"ferias","source":null,"source_id":null,"validated":true}, 
 {"id":1914,"data":"2026-07-24","hora_inicio":null,"hora_fim":null,"tipo":"Férias","notas":null,"created_at":"2026-06-25T09:11:41.179629+00:00","entry_date":null,"project":"—","start_time":"00:00","end_time":"00:00","hours":5.9,"address":null,"is_auto":true,"dl_tipo":"ferias","source":null,"source_id":null,"validated":true}, 
 {"id":1908,"data":"2026-07-17","hora_inicio":null,"hora_fim":null,"tipo":"Férias","notas":null,"created_at":"2026-06-25T09:11:41.168168+00:00","entry_date":null,"project":"—","start_time":"00:00","end_time":"00:00","hours":5.9,"address":null,"is_auto":true,"dl_tipo":"ferias","source":null,"source_id":null,"validated":true}, 
 {"id":1904,"data":"2026-08-05","hora_inicio":null,"hora_fim":null,"tipo":"Férias","notas":null,"created_at":"2026-06-25T09:11:41.074891+00:00","entry_date":null,"project":"—","start_time":"00:00","end_time":"00:00","hours":5.9,"address":null,"is_auto":true,"dl_tipo":"ferias","source":null,"source_id":null,"validated":false}, 
 {"id":1918,"data":"2026-07-08","hora_inicio":null,"hora_fim":null,"tipo":"Férias","notas":null,"created_at":"2026-06-25T09:11:41.179458+00:00","entry_date":null,"project":"—","start_time":"00:00","end_time":"00:00","hours":5.9,"address":null,"is_auto":true,"dl_tipo":"ferias","source":null,"source_id":null,"validated":true}, 
 {"id":1905,"data":"2026-07-23","hora_inicio":null,"hora_fim":null,"tipo":"Férias","notas":null,"created_at":"2026-06-25T09:11:41.106291+00:00","entry_date":null,"project":"—","start_time":"00:00","end_time":"00:00","hours":5.9,"address":null,"is_auto":true,"dl_tipo":"ferias","source":null,"source_id":null,"validated":true}]